{
    "horoscope": {
        "2022/10/08": [
            {
                "content": "恋愛運がアップ☆あなたのお目当ての人が、近づいて来てくれるかも。時にはワナを仕掛けるような、大胆な行動に出てみて。",
                "item": "フレアースカート",
                "money": 4,
                "total": 4,
                "job": 4,
                "color": "ブラック",
                "day": 8,
                "love": 5,
                "rank": 4,
                "sign": "牡羊座"
            },
            {
                "content": "お気に入りの場所に幸運が待っていそう。お気に入りのカフェで、新作の試食をさせてもらえたりするかも？お一人様行動が吉。",
                "item": "モンブラン",
                "money": 2,
                "total": 3,
                "job": 3,
                "color": "シルバー",
                "day": "",
                "love": 3,
                "rank": 9,
                "sign": "牡牛座"
            },
            {
                "content": "あなたがやりたい仕事について、良い人脈ができそうです。今日は学ぶ姿勢を持ち、色々な人にアドバイスを受けると良さそう。",
                "item": "タンブラー",
                "money": 3,
                "total": 3,
                "job": 3,
                "color": "オレンジ",
                "day": "",
                "love": 3,
                "rank": 8,
                "sign": "双子座"
            },
            {
                "content": "金運が低迷気味。貯金を考えているなら、手堅く貯める手段が一番です。まずは生活費を抑える工夫がポイントになりそう。",
                "item": "スニーカー",
                "money": 2,
                "total": 2,
                "job": 2,
                "color": "ブルー",
                "day": "",
                "love": 3,
                "rank": 10,
                "sign": "蟹座"
            },
            {
                "content": "あなたの夢を、強力にサポートしてくれる人が現れそう。周りにあなたの自信を示すことができれば、さらに事態は好転。",
                "item": "ボディークリーム",
                "money": 3,
                "total": 4,
                "job": 4,
                "color": "パープル",
                "day": "",
                "love": 4,
                "rank": 5,
                "sign": "獅子座"
            },
            {
                "content": "親友になる人との運命的な出会いがある予感。些細なご縁でも、今日は大切にしておきましょう。これから意外な展開があるかも。",
                "item": "ファッション雑誌",
                "money": 3,
                "total": 3,
                "job": 4,
                "color": "ピンク",
                "day": "",
                "love": 4,
                "rank": 6,
                "sign": "乙女座"
            },
            {
                "content": "やる気がアップして、新しいことに挑戦したくなりそう。あなたの得意分野を活かせる、チャンス到来の暗示も！積極的に掴んで。",
                "item": "キャミソール",
                "money": 5,
                "total": 5,
                "job": 5,
                "color": "ゴールド",
                "day": "",
                "love": 5,
                "rank": 1,
                "sign": "天秤座"
            },
            {
                "content": "秋の味覚を楽しみすぎていると、いつの間にか体重アップ…！なんてことも。野菜中心に、ヘルシーなメニューを選んで。",
                "item": "シリアル",
                "money": 2,
                "total": 2,
                "job": 2,
                "color": "ホワイト",
                "day": "",
                "love": 2,
                "rank": 11,
                "sign": "蠍座"
            },
            {
                "content": "今日のショッピングは、見るだけにしておいた方が正解。衝動買いではないつもりの買い物でも、お財布にはダメージが。",
                "item": "ストレートティー",
                "money": 1,
                "total": 1,
                "job": 2,
                "color": "グリーン",
                "day": "",
                "love": 2,
                "rank": 12,
                "sign": "射手座"
            },
            {
                "content": "食欲の秋を楽しめそう。話題のお店のテイクアウトに新作が出ていないかチェックしてみて。お取り寄せなら、家族への贈り物も◎。",
                "item": "ロングブーツ",
                "money": 4,
                "total": 5,
                "job": 5,
                "color": "グレー",
                "day": "",
                "love": 5,
                "rank": 2,
                "sign": "山羊座"
            },
            {
                "content": "ずっと憧れていた人が、あなたに声をかけてくれるかも。進展を焦るよりも、まずは相手へ礼儀を尽くしてみましょう。",
                "item": "ブラウス",
                "money": 3,
                "total": 3,
                "job": 3,
                "color": "イエロー",
                "day": "",
                "love": 4,
                "rank": 7,
                "sign": "水瓶座"
            },
            {
                "content": "身体に良いことを、生活に取り入れると運気アップ。一駅分多く歩いたり、ストレッチをしたりするとダイエットの効果が☆",
                "item": "プリンター",
                "money": 4,
                "total": 4,
                "job": 5,
                "color": "レッド",
                "day": "",
                "love": 5,
                "rank": 3,
                "sign": "魚座"
            }
        ]
    }
}