{"horoscope": {"2022/12/09": [{"content": "終わらない仕事に焦ってしまいそう。誰かの手を借りて正解。気になる異性に声をかけると、いきなりの進展があるかも。", "item": "つけめん", "money": 3, "total": 3, "job": 3, "color": "ブラック", "day": 9, "love": 4, "rank": 7, "sign": "牡羊座"}, {"content": "運気が急上昇。楽しい一日になりそうです。素敵な時間はあっという間に過ぎていくもの。終電の時間を過ぎないように。", "item": "電車の定期券", "money": 3, "total": 3, "job": 3, "color": "パープル", "day": "", "love": 3, "rank": 8, "sign": "牡牛座"}, {"content": "今年一年でお世話になった人を思い浮かべて、感謝のメッセージを送りましょう。クリスマスカードなどを準備するのも◎。", "item": "ビーフシチュー", "money": 3, "total": 4, "job": 4, "color": "グレー", "day": "", "love": 4, "rank": 5, "sign": "双子座"}, {"content": "家の中にツキがある日☆今日はなるべく外出を控えて、部屋でリラックスをしてみましょう。料理をすると運気アップ。", "item": "コッペパン", "money": 4, "total": 4, "job": 4, "color": "レッド", "day": "", "love": 5, "rank": 4, "sign": "蟹座"}, {"content": "家族にプレゼントを贈ると吉。お金のかかっているものよりも、実用性のある小物が喜ばれそう。自分にもご褒美をあげて。", "item": "ホットカーペット", "money": 2, "total": 2, "job": 2, "color": "ピンク", "day": "", "love": 3, "rank": 10, "sign": "獅子座"}, {"content": "これまで関わりのなかった業界の人と出会えるチャンスがありそう。相手の話をよく聞くと、良い情報をたくさん得られそう。", "item": "ハンドバック", "money": 3, "total": 3, "job": 4, "color": "ゴールド", "day": "", "love": 4, "rank": 6, "sign": "乙女座"}, {"content": "年末の用事は計画的に進めることが大事。時間を決めて、集中しましょう。予定を詰め込みすぎないで、余裕のある行動を。", "item": "ウーロン茶", "money": 2, "total": 2, "job": 2, "color": "イエロー", "day": "", "love": 2, "rank": 11, "sign": "天秤座"}, {"content": "電化製品を新調するとGOOD。来年に向けて、気持ちも高まりそうです！流行に惑わされないで、実用性を重視して。", "item": "ロングスカート", "money": 5, "total": 5, "job": 5, "color": "シルバー", "day": "", "love": 5, "rank": 1, "sign": "蠍座"}, {"content": "恋人の悩みを聞いてあげることで運気上昇。デートも盛り上がりそう。プレゼントは身につけるものを選んであげてみて。", "item": "しおり", "money": 1, "total": 1, "job": 2, "color": "ホワイト", "day": "", "love": 2, "rank": 12, "sign": "射手座"}, {"content": "長年の片思いにケリをつけるなら、今日が勝負の日です。自分が一番輝くと思えるファッションに身を包んで、告白をして。", "item": "ベーコン", "money": 2, "total": 3, "job": 3, "color": "ブルー", "day": "", "love": 3, "rank": 9, "sign": "山羊座"}, {"content": "自己改善の意欲が高まる日。ダイエット中なら、スイーツは半分だけにするなど工夫して。来年に向けて結果を出せそう♪", "item": "しょうゆ", "money": 4, "total": 4, "job": 5, "color": "グリーン", "day": "", "love": 5, "rank": 3, "sign": "水瓶座"}, {"content": "年末に向けて、やり残したことがないか最終チェックをしてみましょう。今なら、今年中に気持ちよく終わらせることも可能！", "item": "ジャズのCD", "money": 4, "total": 5, "job": 5, "color": "オレンジ", "day": "", "love": 5, "rank": 2, "sign": "魚座"}]}}